{
    "date": 1704258000000,
    "rounds": [
        {
            "year": 2018,
            "event": "For the first time in history, all five major storm surge gates in the Netherlands are closed simultaneously in the wake of a storm.",
            "births": [],
            "deaths": [
                "Colin Brumby, Australian composer"
            ]
        },
        {
            "year": 2009,
            "event": "The first block of the blockchain of the decentralized payment system Bitcoin, called the Genesis block, is established by the creator of the system, Satoshi Nakamoto.",
            "births": [],
            "deaths": [
                "Betty Freeman, American philanthropist and photographer",
                "Pat Hingle, American actor",
                "Hisayasu Nagata, Japanese politician"
            ]
        },
        {
            "year": 1947,
            "event": "Proceedings of the U.S. Congress are televised for the first time.",
            "births": [
                "Fran Cotton, English rugby player",
                "Zulema, American singer-songwriter"
            ],
            "deaths": []
        },
        {
            "year": 1920,
            "event": "Over 640 are killed after a magnitude 6.4 earthquake strikes the Mexican states Puebla and Veracruz.",
            "births": [
                "Siegfried Buback, German lawyer and politician, Attorney General of Germany"
            ],
            "deaths": []
        },
        {
            "year": 1911,
            "event": "A gun battle in the East End of London leaves two dead. It sparked a political row over the involvement of then-Home Secretary Winston Churchill.",
            "births": [],
            "deaths": [
                "Alexandros Papadiamantis, Greek author and poet"
            ]
        }
    ]
}